pymops/__init__.py
pymops/define_dqn.py
pymops/environ.py
pymops/madqn.py
pymops/main.py
pymops/replaymemory.py
pymops/schedules.py
pymops/data/demand_profiles.csv
pymops/data/supply_profiles.csv
pymops-1.0.5.dist-info/LICENSE.txt
pymops-1.0.5.dist-info/METADATA
pymops-1.0.5.dist-info/WHEEL
pymops-1.0.5.dist-info/top_level.txt
pymops-1.0.5.dist-info/RECORD
