Metadata-Version: 2.1
Name: pymops
Version: 1.0.5
Summary: A multi-agent simulation-based optimization package for power scheduling
Home-page: https://github.com/awolseid/pymops
Author: Awol Seid Ebrie and Young Jin Kim
Author-email: es.awol@gmail.com
License: MIT
Project-URL: Bug Tracker, https://github.com/awolseid/pymops
Keywords: Economic Dispach,Power Scheduling,Reinforcement Learning,Unit Commitment
Classifier: Programming Language :: Python :: 3
Classifier: License :: OSI Approved :: MIT License
Classifier: Operating System :: OS Independent
Requires-Python: >=3.9
License-File: LICENSE.txt
Requires-Dist: numpy
Requires-Dist: pandas
Requires-Dist: scipy
Requires-Dist: torch
Requires-Dist: tqdm
